{"updated":"2026-06-06 15:40 UTC","season":2026,"league":{"challenges":3891,"overturned":2054,"rate":0.5278848625032125,"per_team":129.7,"games_logged":948},"teams":[{"team":"Detroit Tigers","abbr":"DET","chal_off":69,"chal_def":53,"chal":122,"overturned":73,"rate":0.5983606557377049,"rate_off":0.5072463768115942,"rate_def":0.7169811320754716,"win_pct":0.406,"era":4.0,"run_diff":-21},{"team":"Texas Rangers","abbr":"TEX","chal_off":55,"chal_def":48,"chal":103,"overturned":61,"rate":0.5922330097087378,"rate_off":0.5454545454545454,"rate_def":0.6458333333333334,"win_pct":0.492,"era":3.7,"run_diff":10},{"team":"Arizona Diamondbacks","abbr":"AZ","chal_off":52,"chal_def":55,"chal":107,"overturned":63,"rate":0.5887850467289719,"rate_off":0.5192307692307693,"rate_def":0.6545454545454545,"win_pct":0.524,"era":4.16,"run_diff":-9},{"team":"Miami Marlins","abbr":"MIA","chal_off":47,"chal_def":112,"chal":159,"overturned":93,"rate":0.5849056603773585,"rate_off":0.5531914893617021,"rate_def":0.5982142857142857,"win_pct":0.453,"era":4.31,"run_diff":-24},{"team":"Cincinnati Reds","abbr":"CIN","chal_off":64,"chal_def":58,"chal":122,"overturned":71,"rate":0.5819672131147541,"rate_off":0.5,"rate_def":0.6724137931034483,"win_pct":0.5,"era":4.81,"run_diff":-48},{"team":"Kansas City Royals","abbr":"KC","chal_off":54,"chal_def":82,"chal":136,"overturned":79,"rate":0.5808823529411765,"rate_off":0.5555555555555556,"rate_def":0.5975609756097561,"win_pct":0.391,"era":4.46,"run_diff":-50},{"team":"Chicago Cubs","abbr":"CHC","chal_off":58,"chal_def":68,"chal":126,"overturned":73,"rate":0.5793650793650794,"rate_off":0.43103448275862066,"rate_def":0.7058823529411765,"win_pct":0.516,"era":4.39,"run_diff":3},{"team":"Athletics","abbr":"ATH","chal_off":58,"chal_def":87,"chal":145,"overturned":82,"rate":0.5655172413793104,"rate_off":0.5862068965517241,"rate_def":0.5517241379310345,"win_pct":0.476,"era":4.47,"run_diff":-37},{"team":"Los Angeles Dodgers","abbr":"LAD","chal_off":52,"chal_def":65,"chal":117,"overturned":66,"rate":0.5641025641025641,"rate_off":0.5,"rate_def":0.6153846153846154,"win_pct":0.641,"era":3.03,"run_diff":134},{"team":"San Diego Padres","abbr":"SD","chal_off":45,"chal_def":71,"chal":116,"overturned":65,"rate":0.5603448275862069,"rate_off":0.4444444444444444,"rate_def":0.6338028169014085,"win_pct":0.516,"era":3.95,"run_diff":-15},{"team":"St. Louis Cardinals","abbr":"STL","chal_off":51,"chal_def":66,"chal":117,"overturned":65,"rate":0.5555555555555556,"rate_off":0.4117647058823529,"rate_def":0.6666666666666666,"win_pct":0.541,"era":4.13,"run_diff":-5},{"team":"New York Yankees","abbr":"NYY","chal_off":69,"chal_def":74,"chal":143,"overturned":77,"rate":0.5384615384615384,"rate_off":0.4782608695652174,"rate_def":0.5945945945945946,"win_pct":0.587,"era":3.3,"run_diff":91},{"team":"Minnesota Twins","abbr":"MIN","chal_off":83,"chal_def":83,"chal":166,"overturned":89,"rate":0.536144578313253,"rate_off":0.4457831325301205,"rate_def":0.6265060240963856,"win_pct":0.462,"era":4.61,"run_diff":-24},{"team":"Houston Astros","abbr":"HOU","chal_off":69,"chal_def":71,"chal":140,"overturned":75,"rate":0.5357142857142857,"rate_off":0.5942028985507246,"rate_def":0.4788732394366197,"win_pct":0.446,"era":4.97,"run_diff":-35},{"team":"Milwaukee Brewers","abbr":"MIL","chal_off":44,"chal_def":87,"chal":131,"overturned":69,"rate":0.5267175572519084,"rate_off":0.4090909090909091,"rate_def":0.5862068965517241,"win_pct":0.623,"era":3.3,"run_diff":91},{"team":"New York Mets","abbr":"NYM","chal_off":63,"chal_def":70,"chal":133,"overturned":70,"rate":0.5263157894736842,"rate_off":0.49206349206349204,"rate_def":0.5571428571428572,"win_pct":0.444,"era":3.77,"run_diff":-8},{"team":"Philadelphia Phillies","abbr":"PHI","chal_off":64,"chal_def":58,"chal":122,"overturned":64,"rate":0.5245901639344263,"rate_off":0.4375,"rate_def":0.6206896551724138,"win_pct":0.54,"era":4.0,"run_diff":-20},{"team":"Colorado Rockies","abbr":"COL","chal_off":73,"chal_def":79,"chal":152,"overturned":79,"rate":0.5197368421052632,"rate_off":0.410958904109589,"rate_def":0.620253164556962,"win_pct":0.375,"era":5.48,"run_diff":-85},{"team":"Atlanta Braves","abbr":"ATL","chal_off":58,"chal_def":79,"chal":137,"overturned":71,"rate":0.5182481751824818,"rate_off":0.39655172413793105,"rate_def":0.6075949367088608,"win_pct":0.672,"era":3.22,"run_diff":112},{"team":"Seattle Mariners","abbr":"SEA","chal_off":65,"chal_def":68,"chal":133,"overturned":68,"rate":0.5112781954887218,"rate_off":0.4153846153846154,"rate_def":0.6029411764705882,"win_pct":0.516,"era":3.53,"run_diff":26},{"team":"Tampa Bay Rays","abbr":"TB","chal_off":54,"chal_def":76,"chal":130,"overturned":66,"rate":0.5076923076923077,"rate_off":0.4444444444444444,"rate_def":0.5526315789473685,"win_pct":0.617,"era":3.95,"run_diff":11},{"team":"Toronto Blue Jays","abbr":"TOR","chal_off":60,"chal_def":57,"chal":117,"overturned":59,"rate":0.5042735042735043,"rate_off":0.5,"rate_def":0.5087719298245614,"win_pct":0.469,"era":4.04,"run_diff":-17},{"team":"Los Angeles Angels","abbr":"LAA","chal_off":67,"chal_def":80,"chal":147,"overturned":74,"rate":0.5034013605442177,"rate_off":0.40298507462686567,"rate_def":0.5875,"win_pct":0.375,"era":4.78,"run_diff":-52},{"team":"Baltimore Orioles","abbr":"BAL","chal_off":66,"chal_def":45,"chal":111,"overturned":55,"rate":0.4954954954954955,"rate_off":0.5151515151515151,"rate_def":0.4666666666666667,"win_pct":0.484,"era":4.58,"run_diff":-27},{"team":"San Francisco Giants","abbr":"SF","chal_off":62,"chal_def":64,"chal":126,"overturned":60,"rate":0.47619047619047616,"rate_off":0.46774193548387094,"rate_def":0.484375,"win_pct":0.406,"era":4.56,"run_diff":-48},{"team":"Chicago White Sox","abbr":"CWS","chal_off":56,"chal_def":100,"chal":156,"overturned":74,"rate":0.47435897435897434,"rate_off":0.4642857142857143,"rate_def":0.48,"win_pct":0.524,"era":4.32,"run_diff":9},{"team":"Boston Red Sox","abbr":"BOS","chal_off":54,"chal_def":41,"chal":95,"overturned":43,"rate":0.45263157894736844,"rate_off":0.4074074074074074,"rate_def":0.5121951219512195,"win_pct":0.435,"era":3.83,"run_diff":-4},{"team":"Washington Nationals","abbr":"WSH","chal_off":55,"chal_def":69,"chal":124,"overturned":56,"rate":0.45161290322580644,"rate_off":0.41818181818181815,"rate_def":0.4782608695652174,"win_pct":0.5,"era":4.65,"run_diff":3},{"team":"Cleveland Guardians","abbr":"CLE","chal_off":71,"chal_def":69,"chal":140,"overturned":63,"rate":0.45,"rate_off":0.36619718309859156,"rate_def":0.5362318840579711,"win_pct":0.554,"era":3.72,"run_diff":5},{"team":"Pittsburgh Pirates","abbr":"PIT","chal_off":66,"chal_def":52,"chal":118,"overturned":51,"rate":0.4322033898305085,"rate_off":0.4090909090909091,"rate_def":0.46153846153846156,"win_pct":0.531,"era":4.05,"run_diff":34}],"umpires":[{"umpire":"Felix Neon","challenges":15,"overturned":12,"games":2,"rate":0.8},{"umpire":"CB Bucknor","challenges":9,"overturned":7,"games":2,"rate":0.7777777777777778},{"umpire":"Andy Fletcher","challenges":40,"overturned":29,"games":9,"rate":0.725},{"umpire":"Todd Tichenor","challenges":43,"overturned":29,"games":12,"rate":0.6744186046511628},{"umpire":"Jacob Metz","challenges":33,"overturned":22,"games":6,"rate":0.6666666666666666},{"umpire":"Chris Segal","challenges":54,"overturned":36,"games":11,"rate":0.6666666666666666},{"umpire":"Clint Vondrak","challenges":24,"overturned":16,"games":10,"rate":0.6666666666666666},{"umpire":"Brian Walsh","challenges":48,"overturned":31,"games":10,"rate":0.6458333333333334},{"umpire":"Stu Scheurwater","challenges":45,"overturned":29,"games":9,"rate":0.6444444444444445},{"umpire":"Hunter Wendelstedt","challenges":62,"overturned":39,"games":12,"rate":0.6290322580645161},{"umpire":"Paul Clemons","challenges":35,"overturned":22,"games":10,"rate":0.6285714285714286},{"umpire":"Ron Kulpa","challenges":32,"overturned":20,"games":6,"rate":0.625},{"umpire":"Mike Estabrook","challenges":52,"overturned":32,"games":11,"rate":0.6153846153846154},{"umpire":"John Bacon","challenges":44,"overturned":27,"games":8,"rate":0.6136363636363636},{"umpire":"Jim Wolf","challenges":41,"overturned":25,"games":8,"rate":0.6097560975609756},{"umpire":"Willie Traynor","challenges":41,"overturned":25,"games":11,"rate":0.6097560975609756},{"umpire":"Doug Eddings","challenges":46,"overturned":28,"games":11,"rate":0.6086956521739131},{"umpire":"Manny Gonzalez","challenges":61,"overturned":37,"games":12,"rate":0.6065573770491803},{"umpire":"Ramon De Jesus","challenges":48,"overturned":29,"games":9,"rate":0.6041666666666666},{"umpire":"Rob Drake","challenges":55,"overturned":33,"games":13,"rate":0.6},{"umpire":"Lance Barrett","challenges":57,"overturned":34,"games":13,"rate":0.5964912280701754},{"umpire":"Adrian Johnson","challenges":37,"overturned":22,"games":7,"rate":0.5945945945945946},{"umpire":"Alfonso M\u00e1rquez","challenges":39,"overturned":23,"games":11,"rate":0.5897435897435898},{"umpire":"Chad Whitson","challenges":46,"overturned":27,"games":11,"rate":0.5869565217391305},{"umpire":"Chad Fairchild","challenges":46,"overturned":27,"games":11,"rate":0.5869565217391305},{"umpire":"Sean Barber","challenges":57,"overturned":33,"games":12,"rate":0.5789473684210527},{"umpire":"Marvin Hudson","challenges":40,"overturned":23,"games":12,"rate":0.575},{"umpire":"Roberto Ortiz","challenges":47,"overturned":27,"games":10,"rate":0.574468085106383},{"umpire":"Charlie Ramos","challenges":42,"overturned":24,"games":8,"rate":0.5714285714285714},{"umpire":"Malachi Moore","challenges":51,"overturned":29,"games":13,"rate":0.5686274509803921},{"umpire":"Brock Ballou","challenges":37,"overturned":21,"games":9,"rate":0.5675675675675675},{"umpire":"Dan Bellino","challenges":60,"overturned":34,"games":13,"rate":0.5666666666666667},{"umpire":"Dan Iassogna","challenges":53,"overturned":30,"games":12,"rate":0.5660377358490566},{"umpire":"Gabe Morales","challenges":39,"overturned":22,"games":10,"rate":0.5641025641025641},{"umpire":"Laz Diaz","challenges":64,"overturned":36,"games":13,"rate":0.5625},{"umpire":"Bill Miller","challenges":50,"overturned":28,"games":12,"rate":0.56},{"umpire":"Cory Blaser","challenges":40,"overturned":22,"games":10,"rate":0.55},{"umpire":"Mark Wegner","challenges":44,"overturned":24,"games":12,"rate":0.5454545454545454},{"umpire":"Mike Muchlinski","challenges":46,"overturned":25,"games":11,"rate":0.5434782608695652},{"umpire":"Brian O'Nora","challenges":41,"overturned":22,"games":9,"rate":0.5365853658536586},{"umpire":"Ben May","challenges":41,"overturned":22,"games":11,"rate":0.5365853658536586},{"umpire":"Alex MacKay","challenges":43,"overturned":23,"games":10,"rate":0.5348837209302325},{"umpire":"Nick Mahrley","challenges":34,"overturned":18,"games":10,"rate":0.5294117647058824},{"umpire":"Tom Hanahan","challenges":53,"overturned":28,"games":12,"rate":0.5283018867924528},{"umpire":"Tripp Gibson","challenges":44,"overturned":23,"games":12,"rate":0.5227272727272727},{"umpire":"Ryan Blakney","challenges":46,"overturned":24,"games":12,"rate":0.5217391304347826},{"umpire":"Carlos Torres","challenges":48,"overturned":25,"games":13,"rate":0.5208333333333334},{"umpire":"Nestor Ceja","challenges":48,"overturned":25,"games":13,"rate":0.5208333333333334},{"umpire":"Ryan Wills","challenges":48,"overturned":25,"games":12,"rate":0.5208333333333334},{"umpire":"Junior Valentine","challenges":37,"overturned":19,"games":9,"rate":0.5135135135135135},{"umpire":"Alan Porter","challenges":39,"overturned":20,"games":10,"rate":0.5128205128205128},{"umpire":"Jeremie Rehak","challenges":45,"overturned":23,"games":10,"rate":0.5111111111111111},{"umpire":"Bruce Dreckman","challenges":53,"overturned":27,"games":12,"rate":0.5094339622641509},{"umpire":"Jen Pawol","challenges":28,"overturned":14,"games":6,"rate":0.5},{"umpire":"Will Little","challenges":58,"overturned":29,"games":13,"rate":0.5},{"umpire":"D.J. Reyburn","challenges":46,"overturned":23,"games":11,"rate":0.5},{"umpire":"Dan Merzel","challenges":45,"overturned":22,"games":11,"rate":0.4888888888888889},{"umpire":"Brennan Miller","challenges":45,"overturned":22,"games":11,"rate":0.4888888888888889},{"umpire":"Chris Conroy","challenges":43,"overturned":21,"games":11,"rate":0.4883720930232558},{"umpire":"Chris Guccione","challenges":58,"overturned":28,"games":12,"rate":0.4827586206896552},{"umpire":"Vic Carapazza","challenges":54,"overturned":26,"games":14,"rate":0.48148148148148145},{"umpire":"Edwin Moscoso","challenges":50,"overturned":24,"games":11,"rate":0.48},{"umpire":"Steven Jaschinski","challenges":23,"overturned":11,"games":5,"rate":0.4782608695652174},{"umpire":"Jordan Baker","challenges":46,"overturned":22,"games":13,"rate":0.4782608695652174},{"umpire":"Ryan Additon","challenges":61,"overturned":29,"games":12,"rate":0.47540983606557374},{"umpire":"Adam Hamari","challenges":40,"overturned":19,"games":12,"rate":0.475},{"umpire":"Quinn Wolcott","challenges":55,"overturned":26,"games":12,"rate":0.4727272727272727},{"umpire":"Shane Livensparger","challenges":36,"overturned":17,"games":10,"rate":0.4722222222222222},{"umpire":"Jansen Visconti","challenges":41,"overturned":19,"games":11,"rate":0.4634146341463415},{"umpire":"Austin Jones","challenges":41,"overturned":19,"games":9,"rate":0.4634146341463415},{"umpire":"Lance Barksdale","challenges":42,"overturned":19,"games":11,"rate":0.4523809523809524},{"umpire":"James Jean","challenges":45,"overturned":20,"games":12,"rate":0.4444444444444444},{"umpire":"Adam Beck","challenges":54,"overturned":24,"games":12,"rate":0.4444444444444444},{"umpire":"Nate Tomlinson","challenges":34,"overturned":15,"games":11,"rate":0.4411764705882353},{"umpire":"Jonathan Parra","challenges":25,"overturned":11,"games":6,"rate":0.44},{"umpire":"Edwin Jimenez","challenges":21,"overturned":9,"games":6,"rate":0.42857142857142855},{"umpire":"James Hoye","challenges":49,"overturned":21,"games":12,"rate":0.42857142857142855},{"umpire":"Alex Tosi","challenges":42,"overturned":18,"games":12,"rate":0.42857142857142855},{"umpire":"John Libka","challenges":35,"overturned":15,"games":12,"rate":0.42857142857142855},{"umpire":"Nic Lentz","challenges":57,"overturned":24,"games":12,"rate":0.42105263157894735},{"umpire":"John Tumpane","challenges":46,"overturned":19,"games":13,"rate":0.41304347826086957},{"umpire":"Mark Ripperger","challenges":44,"overturned":18,"games":12,"rate":0.4090909090909091},{"umpire":"Scott Barry","challenges":40,"overturned":16,"games":11,"rate":0.4},{"umpire":"Emil Jimenez","challenges":39,"overturned":15,"games":9,"rate":0.38461538461538464},{"umpire":"Tyler Jones","challenges":26,"overturned":10,"games":7,"rate":0.38461538461538464},{"umpire":"Erich Bacchus","challenges":34,"overturned":13,"games":11,"rate":0.38235294117647056},{"umpire":"Derek Thomas","challenges":40,"overturned":15,"games":9,"rate":0.375},{"umpire":"David Rackley","challenges":46,"overturned":17,"games":13,"rate":0.3695652173913043},{"umpire":"Dexter Kelley","challenges":27,"overturned":9,"games":6,"rate":0.3333333333333333},{"umpire":"Louie Krupa","challenges":24,"overturned":8,"games":5,"rate":0.3333333333333333},{"umpire":"Dillon Wilson","challenges":3,"overturned":0,"games":2,"rate":0.0}],"min_ump_chal":20,"min_team_chal":8,"players":{"batter":[{"name":"CJ Abrams","team":"WSH","challenges":7,"overturned":7,"rate":1.0},{"name":"Isaac Paredes","team":"HOU","challenges":6,"overturned":6,"rate":1.0},{"name":"Nick Kurtz","team":"ATH","challenges":7,"overturned":6,"rate":0.8571428571428571},{"name":"Otto Lopez","team":"MIA","challenges":5,"overturned":4,"rate":0.8},{"name":"Francisco Alvarez","team":"NYM","challenges":5,"overturned":4,"rate":0.8},{"name":"Jung Hoo Lee","team":"SF","challenges":5,"overturned":4,"rate":0.8},{"name":"Owen Caissie","team":"MIA","challenges":5,"overturned":4,"rate":0.8},{"name":"Brent Rooker","team":"ATH","challenges":9,"overturned":7,"rate":0.7777777777777778},{"name":"Xander Bogaerts","team":"SD","challenges":12,"overturned":9,"rate":0.75},{"name":"Davis Schneider","team":"TOR","challenges":12,"overturned":9,"rate":0.75},{"name":"Aaron Judge","team":"NYY","challenges":8,"overturned":6,"rate":0.75},{"name":"Maikel Garcia","team":"KC","challenges":12,"overturned":9,"rate":0.75},{"name":"Marcus Semien","team":"NYM","challenges":7,"overturned":5,"rate":0.7142857142857143},{"name":"Ryan O'Hearn","team":"PIT","challenges":7,"overturned":5,"rate":0.7142857142857143},{"name":"Rhys Hoskins","team":"CLE","challenges":7,"overturned":5,"rate":0.7142857142857143},{"name":"Mike Trout","team":"LAA","challenges":7,"overturned":5,"rate":0.7142857142857143},{"name":"Teoscar Hernandez","team":"LAD","challenges":10,"overturned":7,"rate":0.7},{"name":"Jose Altuve","team":"HOU","challenges":13,"overturned":9,"rate":0.6923076923076923},{"name":"Jakob Marsee","team":"MIA","challenges":6,"overturned":4,"rate":0.6666666666666666},{"name":"Kevin McGonigle","team":"DET","challenges":15,"overturned":10,"rate":0.6666666666666666},{"name":"Christian Walker","team":"HOU","challenges":9,"overturned":6,"rate":0.6666666666666666},{"name":"Brayan Rocchio","team":"CLE","challenges":9,"overturned":6,"rate":0.6666666666666666},{"name":"Gabriel Moreno","team":"AZ","challenges":9,"overturned":6,"rate":0.6666666666666666},{"name":"Samuel Basallo","team":"BAL","challenges":9,"overturned":6,"rate":0.6666666666666666},{"name":"Jake Burger","team":"TEX","challenges":6,"overturned":4,"rate":0.6666666666666666}],"catcher":[{"name":"Rodolfo Duran","team":"SD","challenges":9,"overturned":8,"rate":0.8888888888888888},{"name":"Adrian Del Castillo","team":"AZ","challenges":6,"overturned":5,"rate":0.8333333333333334},{"name":"Carson Kelly","team":"CHC","challenges":29,"overturned":24,"rate":0.8275862068965517},{"name":"J.T. Realmuto","team":"PHI","challenges":25,"overturned":20,"rate":0.8},{"name":"Mitch Garver","team":"SEA","challenges":20,"overturned":16,"rate":0.8},{"name":"Sandy Leon","team":"ATL","challenges":15,"overturned":12,"rate":0.8},{"name":"Travis d'Arnaud","team":"LAA","challenges":10,"overturned":8,"rate":0.8},{"name":"Salvador Perez","team":"KC","challenges":44,"overturned":33,"rate":0.75},{"name":"P.J. Higgins","team":"CIN","challenges":8,"overturned":6,"rate":0.75},{"name":"Drake Baldwin","team":"ATL","challenges":27,"overturned":20,"rate":0.7407407407407407},{"name":"Danny Jansen","team":"TEX","challenges":18,"overturned":13,"rate":0.7222222222222222},{"name":"Dillon Dingler","team":"DET","challenges":42,"overturned":30,"rate":0.7142857142857143},{"name":"Pedro Pages","team":"STL","challenges":35,"overturned":25,"rate":0.7142857142857143},{"name":"Agustin Ramirez","team":"MIA","challenges":31,"overturned":22,"rate":0.7096774193548387},{"name":"Tyler Stephenson","team":"CIN","challenges":47,"overturned":33,"rate":0.7021276595744681},{"name":"Gabriel Moreno","team":"AZ","challenges":22,"overturned":15,"rate":0.6818181818181818},{"name":"Victor Caratini","team":"MIN","challenges":39,"overturned":26,"rate":0.6666666666666666},{"name":"Connor Wong","team":"BOS","challenges":9,"overturned":6,"rate":0.6666666666666666},{"name":"Will Smith","team":"LAD","challenges":47,"overturned":31,"rate":0.6595744680851063},{"name":"Hunter Goodman","team":"COL","challenges":44,"overturned":29,"rate":0.6590909090909091},{"name":"Kyle Higashioka","team":"TEX","challenges":26,"overturned":17,"rate":0.6538461538461539},{"name":"Miguel Amaya","team":"CHC","challenges":34,"overturned":22,"rate":0.6470588235294118},{"name":"Luis Campusano","team":"SD","challenges":28,"overturned":18,"rate":0.6428571428571429},{"name":"Gary Sanchez","team":"MIL","challenges":14,"overturned":9,"rate":0.6428571428571429},{"name":"Ivan Herrera","team":"STL","challenges":25,"overturned":16,"rate":0.64}],"pitcher":[{"name":"Freddy Peralta","team":"NYM","challenges":5,"overturned":3,"rate":0.6}]},"correlation":{"win_pct":{"r":-0.049,"n":30},"era":{"r":-0.017,"n":30},"run_diff":{"r":-0.067,"n":30}},"trend":[{"date":"2026-06-06","challenges":3891,"overturned":2054,"rate":0.5278848625032125}]}